digy/__init__.py
digy/auth.py
digy/cli.py
digy/deployer.py
digy/environment.py
digy/file_utils.py
digy/interactive.py
digy/loader.py
digy/manifest.yml
digy/templates/Dockerfile.template
digy/version.py
digy-0.2.10.dist-info/LICENSE
digy-0.2.10.dist-info/METADATA
digy-0.2.10.dist-info/WHEEL
digy-0.2.10.dist-info/entry_points.txt
digy-0.2.10.dist-info/RECORD
