Metadata-Version: 2.3
Name: digy
Version: 0.2.10
Summary: Do Interactive Git deploY - Deploy Python applications from Git repositories in isolated environments with interactive menu
Keywords: deployment,git,python,interactive,isolated
Author: Tom Sapletta
Author-email: info@softreck.dev
Requires-Python: >=3.9
Classifier: Development Status :: 3 - Alpha
Classifier: Intended Audience :: Developers
Classifier: License :: OSI Approved :: Apache Software License
Classifier: Programming Language :: Python :: 3
Classifier: Programming Language :: Python :: 3.9
Classifier: Programming Language :: Python :: 3.10
Classifier: Programming Language :: Python :: 3.11
Classifier: Programming Language :: Python :: 3.12
Classifier: Programming Language :: Python :: 3.13
Classifier: Programming Language :: Python :: 3.8
Requires-Dist: click (>=8.1.7,<9.0.0)
Requires-Dist: docker (>=6.1.3,<7.0.0)
Requires-Dist: gitpython (>=3.1.40,<4.0.0)
Requires-Dist: psutil (>=5.9.6,<6.0.0)
Requires-Dist: python-dotenv (>=1.0.0,<2.0.0)
Requires-Dist: pyyaml (>=6.0.1,<7.0.0)
Requires-Dist: readchar (>=4.0.4,<5.0.0)
Requires-Dist: requests (>=2.31.0,<3.0.0)
Requires-Dist: rich (>=13.7.0,<14.0.0)
Requires-Dist: virtualenv (>=20.24.6,<21.0.0)
Project-URL: Documentation, https://github.com/pyfunc/digy
Project-URL: Homepage, https://github.com/pyfunc/digy
Project-URL: Repository, https://github.com/pyfunc/digy
